{
  "navigtions": [],
  "services": [
    {
      "title": "ux design",
      "subtitle": "mobile app,website",
      "img_url": "../icons/ux-interface.png",
      "num_img": "../icons/01.png",
      "content": "Lorem Ipsum is simply dummy text of the printing and typesetting industry. Lorem Ipsum has been the industry's standard dummy text ever since the 1500s.",
      "status":"Active",
      "id": 1
    },
    {
      "title": "game design",
      "subtitle": "mobile app,website",
      "img_url": "../icons/gaming.png",
      "num_img": "../icons/02.png",
      "content": "Lorem Ipsum is simply dummy text of the printing and typesetting industry. Lorem Ipsum has been the industry's standard dummy text ever since the 1500s.",
      "status":"Active",
      "id": 2
    },
    {
      "title": "graphic design",
      "subtitle": "mobile app,website",
      "img_url": "../icons/design.png",
      "num_img": "../icons/03.png",
      "content": "Lorem Ipsum is simply dummy text of the printing and typesetting industry. Lorem Ipsum has been the industry's standard dummy text ever since the 1500s.",
      "status":"Active",
      "id": 3
    },
    {
      "title": "web design",
      "subtitle": "mobile app,website",
      "img_url": "../icons/web-design.png",
      "num_img": "../icons/04.png",
      "content": "Lorem Ipsum is simply dummy text of the printing and typesetting industry. Lorem Ipsum has been the industry's standard dummy text ever since the 1500s.",
      "status":"Active",
      "id": 4
    },
    {
      "title": "app development",
      "subtitle": "mobile app,website",
      "img_url": "../icons/mobile-development.png",
      "num_img": "../icons/05.png",
      "content": "Lorem Ipsum is simply dummy text of the printing and typesetting industry. Lorem Ipsum has been the industry's standard dummy text ever since the 1500s.",
      "status":"Active",
      "id": 5
    },
    {
      "title": "digital marketing",
      "subtitle": "mobile app,website",
      "img_url": "../icons/digital-marketing.png",
      "num_img": "../icons/06.png",
      "content": "Lorem Ipsum is simply dummy text of the printing and typesetting industry. Lorem Ipsum has been the industry's standard dummy text ever since the 1500s.",
      "status":"Active",
      "id": 6
    }
  ]
}